rconnet/__init__.py
rconnet/banmanager.py
rconnet/maplist.py
rconnet/rconbf2142/__init__.py
rconnet/rconbf2142/default.py
rconnet/rconbf2142/modmanager.py
rconnet/rconbf2142/modules/__init__.py
rconnet/rconbf2142/modules/modmanager/__init__.py
rconnet/rconbf2142/modules/modmanager/bf2cc.py
rconnet/settings.py
rconnet/tcpclient.py
rconnet-0.1.1.dist-info/LICENSE
rconnet-0.1.1.dist-info/METADATA
rconnet-0.1.1.dist-info/WHEEL
rconnet-0.1.1.dist-info/RECORD
