Metadata-Version: 2.1
Name: rconnet
Version: 0.1.1
Summary: Python RCON client for the Battlefield 2142 server
Home-page: https://github.com/VordyV/rconnet
License: MIT
Keywords: rcon,client,modmanager,battlefield
Author: Vordy
Author-email: 61288579+VordyV@users.noreply.github.com
Requires-Python: >=3.12,<3.14
Classifier: License :: OSI Approved :: MIT License
Classifier: Programming Language :: Python :: 3
Requires-Dist: pdoc (>=15.0.1,<16.0.0)
Requires-Dist: sphinx (>=8.1.3,<9.0.0)
Project-URL: Documentation, https://github.com/VordyV/rconnet/wiki
Project-URL: Repository, https://github.com/VordyV/rconnet
